mi_paquete/__init__.py
mi_paquete/modulo1.py
mi_paquete/modulo2.py
modulo_juan-0.1.0.dist-info/LICENSE
modulo_juan-0.1.0.dist-info/METADATA
modulo_juan-0.1.0.dist-info/WHEEL
modulo_juan-0.1.0.dist-info/top_level.txt
modulo_juan-0.1.0.dist-info/RECORD
