Metadata-Version: 2.1
Name: modulo_juan
Version: 0.1.0
Summary: Paquete creado con fines educativos. Mas informacion: github.com/Duz-Dev
Author-email: Ruben Chavez <pablo.dev.academy@gmail.com>
License: MIT License
Project-URL: Homepage, https://github.com/Duz-Dev/modulo-juan
Project-URL: Download, https://github.com/Duz-Dev/modulo-juan/tarball/0.1.0
Keywords: testing,logging,example
Classifier: Programming Language :: Python :: 3
Classifier: License :: OSI Approved :: MIT License
Classifier: Operating System :: OS Independent
License-File: LICENSE
Requires-Dist: modulo_pablo==0.1.4
